setup.cfg
setup.py
codap/__init__.py
codap.egg-info/PKG-INFO
codap.egg-info/SOURCES.txt
codap.egg-info/dependency_links.txt
codap.egg-info/top_level.txt
tests/__init__.py
tests/test_codap.py