Metadata-Version: 1.0
Name: codap
Version: 0.0.4
Summary: Coroutine Data Access Patterns (mouthful I know) are some data
Home-page: https://github.com/lateefj/codap
Author: Lateef Jackson
Author-email: lateef.jackson@gmail.com
License: BSD
Keywords: gevent eventlet coroutine
Platform: UNKNOWN
Classifier: Development Status :: 3 - Alpha
Classifier: Topic :: Utilities
Classifier: License :: OSI Approved :: BSD License
